{
  "schemaVersion": 1,
  "id": "fabric-biomes-v1",
  "name": "Fabric Biomes API (v1)",
  "version": "${version}",
  "environment": "*",
  "license": "Apache-2.0",
  "icon": "assets/fabric-biomes-v1/icon.png",
  "contact": {
    "homepage": "https://fabricmc.net",
    "irc": "irc://irc.esper.net:6667/legacyfabric",
    "issues": "https://github.com/Legacy-Fabric/fabric/issues",
    "sources": "https://github.com/Legacy-Fabric/fabric"
  },
  "authors": [
    "FabricMC"
  ],
  "depends": {
    "fabricloader": ">=0.4.0"
  },
  "description": "Tools for biome generation and manipulating vanilla biomes",
  "mixins": [
    "fabric-biomes-v1.mixins.json"
  ]
}
